{
  "_schema": {
    "version": "1.0",
    "description": "Cryptographic audit trail of agent state transitions. Each entry's prev_hash links to the previous entry's output_hash."
  },
  "entries": [
    {
      "seq": 1,
      "timestamp": "2026-02-09T16:15:40.780+00:00",
      "task_id": "PLAN-DISCOVERY",
      "pipeline": "plan",
      "stage": "discovery_complete",
      "agent": "planner",
      "input_hash": "sha256:93a6387445d0b21a6d5f8a24ec70f236ce1bd0251f2da6bb883b962a234a5d00",
      "output_hash": "sha256:192191b67e749f4b2c4d4d7c332c8d902b90640dae83adf7e878ef3a6bb65ec4",
      "prev_hash": null,
      "description": "Discovery phase complete: 24 decisions, Light mode, sections 1-5",
      "verdict": null,
      "warnings": [],
      "metadata": {
        "phase": "discovery",
        "decisions_count": 24,
        "depth": "Light",
        "advisory_sources": []
      }
    },
    {
      "seq": 2,
      "timestamp": "2026-02-09T16:24:20.506+00:00",
      "task_id": "PLAN-DEFINE",
      "pipeline": "plan",
      "stage": "definition_complete",
      "agent": "planner",
      "input_hash": "sha256:46e1eb4e3050d55892b499e0c0f930767a297edca42f2707ebd5016f3e68104c",
      "output_hash": "sha256:ec9f09681acfa2fd68266229c82d9ad12375c264cf3c23e0b43017338e8a1d3b",
      "prev_hash": "sha256:192191b67e749f4b2c4d4d7c332c8d902b90640dae83adf7e878ef3a6bb65ec4",
      "description": "Definition phase complete: 28 total decisions, artifacts finalized",
      "verdict": null,
      "warnings": [],
      "metadata": {
        "phase": "definition",
        "decisions_count": 28,
        "competition_incorporated": false,
        "depth": "Light",
        "advisory_sources": []
      }
    },
    {
      "seq": 3,
      "timestamp": "2026-02-09T16:28:46.183+00:00",
      "task_id": "SPEC-ARCH",
      "pipeline": "specialist",
      "stage": "completion",
      "agent": "architect",
      "input_hash": "sha256:eddfb49b453d8975ab40fedfd5ad8877d4c32b8251c737bbacaced1f937e497f",
      "output_hash": "sha256:d8efe385ab3b7becb203ad4cde9425dea6bb606588316c545403dab11faf8926",
      "prev_hash": "sha256:ec9f09681acfa2fd68266229c82d9ad12375c264cf3c23e0b43017338e8a1d3b",
      "description": "Architecture specialist complete: ARCH-01 through ARCH-16",
      "verdict": null,
      "warnings": [],
      "metadata": {
        "decisions_added": [
          "ARCH-01",
          "ARCH-02",
          "ARCH-03",
          "ARCH-04",
          "ARCH-05",
          "ARCH-06",
          "ARCH-07",
          "ARCH-08",
          "ARCH-09",
          "ARCH-10",
          "ARCH-11",
          "ARCH-12",
          "ARCH-13",
          "ARCH-14",
          "ARCH-15",
          "ARCH-16"
        ],
        "advisory_sources": []
      }
    },
    {
      "seq": 4,
      "timestamp": "2026-02-09T16:32:28.768+00:00",
      "task_id": "SPEC-BACK",
      "pipeline": "specialist",
      "stage": "completion",
      "agent": "backend",
      "input_hash": "sha256:e4db83bea95586fa5b19ee12203298ee5a0de029e0e8c714aa0ef84f6c4b5d1e",
      "output_hash": "sha256:857dcb98b47caa3b808e67f1c10ccdd41787182e593f096f91dd5af364cb12c1",
      "prev_hash": "sha256:d8efe385ab3b7becb203ad4cde9425dea6bb606588316c545403dab11faf8926",
      "description": "Backend specialist complete: BACK-01 through BACK-15",
      "verdict": null,
      "warnings": [],
      "metadata": {
        "decisions_added": [
          "BACK-01",
          "BACK-02",
          "BACK-03",
          "BACK-04",
          "BACK-05",
          "BACK-06",
          "BACK-07",
          "BACK-08",
          "BACK-09",
          "BACK-10",
          "BACK-11",
          "BACK-12",
          "BACK-13",
          "BACK-14",
          "BACK-15"
        ],
        "advisory_sources": []
      }
    }
  ],
  "integrity": {
    "last_verified": null,
    "chain_valid": true,
    "broken_links": []
  }
}
